odoo/addons/l10n_br_zip_correios/README.rst
odoo/addons/l10n_br_zip_correios/__init__.py
odoo/addons/l10n_br_zip_correios/__manifest__.py
odoo/addons/l10n_br_zip_correios/i18n/pt_BR.po
odoo/addons/l10n_br_zip_correios/models/__init__.py
odoo/addons/l10n_br_zip_correios/models/l10n_br_zip.py
odoo/addons/l10n_br_zip_correios/models/webservice_client.py
odoo/addons/l10n_br_zip_correios/readme/CONFIGURE.rst
odoo/addons/l10n_br_zip_correios/readme/CONTRIBUTORS.rst
odoo/addons/l10n_br_zip_correios/readme/DESCRIPTION.rst
odoo/addons/l10n_br_zip_correios/readme/INSTALL.rst
odoo/addons/l10n_br_zip_correios/readme/ROADMAP.rst
odoo/addons/l10n_br_zip_correios/readme/USAGE.rst
odoo/addons/l10n_br_zip_correios/static/description/icon.png
odoo/addons/l10n_br_zip_correios/static/description/index.html
odoo/addons/l10n_br_zip_correios/tests/__init__.py
odoo/addons/l10n_br_zip_correios/tests/test_webservice_client.py
odoo12_addon_l10n_br_zip_correios-12.0.1.0.0.99.dev7.dist-info/METADATA
odoo12_addon_l10n_br_zip_correios-12.0.1.0.0.99.dev7.dist-info/WHEEL
odoo12_addon_l10n_br_zip_correios-12.0.1.0.0.99.dev7.dist-info/top_level.txt
odoo12_addon_l10n_br_zip_correios-12.0.1.0.0.99.dev7.dist-info/RECORD
