Metadata-Version: 2.1
Name: odoo12-addon-l10n-br-zip-correios
Version: 12.0.1.0.0.99.dev7
Summary: Address from Brazilian Localization ZIP by Correios
Home-page: http://odoo-brasil.org
Author: KMEE, Odoo Community Association (OCA)
Author-email: support@odoo-community.org
License: AGPL-3
Platform: UNKNOWN
Classifier: Programming Language :: Python
Classifier: Framework :: Odoo
Classifier: License :: OSI Approved :: GNU Affero General Public License v3
Requires-Python: >=3.5
Requires-Dist: odoo12-addon-l10n-br-zip
Requires-Dist: odoo (<12.1dev,>=12.0a)
Requires-Dist: suds-jurko
